mpcurses/__init__.py
mpcurses/mpcurses.py
mpcurses/screen.py
mpcurses-1.0.0.dist-info/METADATA
mpcurses-1.0.0.dist-info/WHEEL
mpcurses-1.0.0.dist-info/namespace_packages.txt
mpcurses-1.0.0.dist-info/top_level.txt
mpcurses-1.0.0.dist-info/zip-safe
mpcurses-1.0.0.dist-info/RECORD
