Metadata-Version: 2.1
Name: mpcurses
Version: 1.0.0
Summary: The mpcurses module facilitates seamless terminal screen updates from child processes within a multiprocessing worker pool, leveraging the curses library for terminal manipulation
Home-page: https://github.com/soda480/mpcurses
Author: Emilio Reyes
Author-email: soda480@gmail.com
Maintainer: 
Maintainer-email: 
License: Apache License, Version 2.0
Classifier: Programming Language :: Python
Classifier: Programming Language :: Python :: 3.8
Classifier: Programming Language :: Python :: 3.9
Classifier: Programming Language :: Python :: 3.10
Classifier: Programming Language :: Python :: 3.11
Classifier: Programming Language :: Python :: 3.12
Requires-Dist: mpmq
